[{"_id":"64484437067f843f04010078","name":"Project 282","nature":"undefined","begin":"2021","end":"2021","team":"wagner,renan,mailson,Hércules,Lucas,Gabriel","technologies":"Android,CouchDB,JavaScript,iOS","softskills":"Initiative to learning,Collaboration,Desire to improve things","method_proj":"\"SCRUM\"","projectId":282,"__v":0},{"_id":"64484437067f843f0401007b","name":"Project 201","nature":"undefined","begin":"2021","end":"2021","team":"wagner,diego,italo,franklin,jose,Renato,Raquel,Almir,Axél,Matheus,Sofia","technologies":"Lua,IOT,Java,iOS,RESTful APIs,JavaScript,JSON","softskills":"Collaboration","method_proj":"\"SCRUM\"","projectId":201,"__v":0},{"_id":"64484437067f843f0401007c","name":"Project 200","nature":"undefined","begin":"2021","end":"2021","team":"wagner,renan,mailson,Hércules,Lucas,Andresso","technologies":"Android,CouchDB,JavaScript,iOS","softskills":"Initiative to learning,Collaboration,Desire to improve things","method_proj":"\"SCRUM\"","projectId":200,"__v":0},{"_id":"64484437067f843f0401007d","name":"Project 196","nature":"undefined","begin":"2021","end":"2021","team":"sergio,amanda,pedro,bruno,fagner,felipe,walter,jose,leandro,gabriel,paulo,Bruno,Lucas,Bruna,Galileu,Rafael,Tiago,Narcizo,Allender,Lucas,Jorge,Joaquim","technologies":"Mobile,JavaScript,RESTful APIs,iOS,Android","softskills":"Initiative to learning","method_proj":"\"SCRUM\"","projectId":196,"__v":0},{"_id":"64484437067f843f0401007e","name":"Project 195","nature":"undefined","begin":"2021","end":"2021","team":"sergio,marcos,vladwoguer,walter,fabiano,fernando,Anderson,paulo,Weverton,Gabriel,Lucas,Mayra,Ícaro","technologies":"MongoDB,iOS,JavaScript,Android","softskills":"Initiative to learning","method_proj":"\"SCRUM\"","projectId":195,"__v":0},{"_id":"644ab1a1581a0b2ed01869ef","name":"","nature":"Similar technology","begin":"","end":"","team":"gil,rivera","technologies":"Javascript,Java","softskills":"Initiative","method_proj":"Scrum","data_proj":"Thu Apr 27 2023 14:32:17 GMT-0300 (Horário Padrão de Brasília)","__v":0},{"_id":"644ba5bd8989b980db840c3d","name":"ISABELLA ","nature":"Similar technology","begin":"2023","end":"2024","team":"well,italy","technologies":"Java,Javascript","softskills":"Initiative","method_proj":"Scrum","data_proj":"Fri Apr 28 2023 07:53:49 GMT-0300 (Horário Padrão de Brasília)","__v":0},{"_id":"644ba8cd6bd79e515162372b","name":"ISABELLA ","nature":"Similar technology","begin":"2023","end":"2024","team":"drunny,pig","technologies":"Javascript,Java","softskills":"Initiative","method_proj":"Scrum","data_proj":"Fri Apr 28 2023 08:06:53 GMT-0300 (Horário Padrão de Brasília)","__v":0},{"_id":"644babf42162d3cf53c4d3e7","name":"ISABELLA ","nature":"Similar technology","begin":"2023","end":"2024","team":"geni,divertig","technologies":"Javascript,Java","softskills":"Initiative","method_proj":"Scrum","data_proj":"Fri Apr 28 2023 08:20:20 GMT-0300 (Horário Padrão de Brasília)","__v":0},{"_id":"644bac94d3078f59a88c2b80","name":"projeto site","nature":"Similar technology","begin":"2023","end":"2024","team":"reflux,perla","technologies":"Javascript,Java","softskills":"Initiative","method_proj":"Scrum","data_proj":"Fri Apr 28 2023 08:23:00 GMT-0300 (Horário Padrão de Brasília)","__v":0},{"_id":"644bc7ca7f74be887a178a8e","name":"teste","nature":"Similar technology","begin":"2023","end":"2024","team":"herz,wedhon","technologies":"Javascript,Java","softskills":"Initiative","method_proj":"Scrum","data_proj":"Fri Apr 28 2023 10:19:06 GMT-0300 (Horário Padrão de Brasília)","__v":0},{"_id":"644e8debf468fbd2ea08faa9","name":"","nature":"Similar technology","begin":"","end":"","team":"Leonardo,filipe","technologies":"ios,html","softskills":"","method_proj":"","data_proj":"Sun Apr 30 2023 12:48:59 GMT-0300 (Horário Padrão de Brasília)","__v":0},{"_id":"644eb4cce60a238a6fb89fb4","name":"","nature":"Similar technology","begin":"","end":"","team":"","technologies":"Javascript,Web","softskills":"","method_proj":"","data_proj":"Sun Apr 30 2023 15:34:52 GMT-0300 (Horário Padrão de Brasília)","__v":0},{"_id":"644ecb5fe60a238a6fb89fbc","name":"é só teimar que dá certo!","nature":"Similar technology","begin":"2023","end":"2024","team":"","technologies":"Javascript,Mobile,Web,ios","softskills":"Initiative","method_proj":"Scrum","data_proj":"Sun Apr 30 2023 17:11:11 GMT-0300 (Horário Padrão de Brasília)","__v":0},{"_id":"644ecbc6e60a238a6fb89fc4","name":"ISABELLA ","nature":"Similar technology","begin":"2023","end":"2024","team":"","technologies":"Javascript,Mobile,Web,ios","softskills":"Creativity","method_proj":"Scrum","data_proj":"Sun Apr 30 2023 17:12:54 GMT-0300 (Horário Padrão de Brasília)","__v":0},{"_id":"644ecc0ee60a238a6fb89fcc","name":"ISABELLA ","nature":"Similar technology","begin":"2023","end":"2024","team":"","technologies":"Javascript,Angular,Mobile","softskills":"Initiative","method_proj":"Scrum","data_proj":"Sun Apr 30 2023 17:14:06 GMT-0300 (Horário Padrão de Brasília)","__v":0},{"_id":"644ecf6ae60a238a6fb89fd4","name":"ISABELLA ","nature":"Similar technology","begin":"2023","end":"2024","team":"Glauco Gomes,filipe ramos","technologies":"Java,Angular,Web","softskills":"Creativity","method_proj":"Scrum","data_proj":"Sun Apr 30 2023 17:28:26 GMT-0300 (Horário Padrão de Brasília)","__v":0},{"_id":"644ed163e60a238a6fb89fdc","name":"","nature":"Similar technology","begin":"","end":"","team":"guilherme neves","technologies":"Angular,Javascript,ios","softskills":"","method_proj":"","data_proj":"Sun Apr 30 2023 17:36:51 GMT-0300 (Horário Padrão de Brasília)","__v":0}]